pycalphad_xml/CEF.rng
pycalphad_xml/MQMQA.rng
pycalphad_xml/__init__.py
pycalphad_xml/core.rng
pycalphad_xml/database.rng
pycalphad_xml/parser.py
pycalphad_xml-0.1.1.dist-info/LICENSE
pycalphad_xml-0.1.1.dist-info/METADATA
pycalphad_xml-0.1.1.dist-info/WHEEL
pycalphad_xml-0.1.1.dist-info/top_level.txt
pycalphad_xml-0.1.1.dist-info/RECORD
