Metadata-Version: 2.1
Name: pycalphad-xml
Version: 0.1.1
Summary: XML database plugin for pycalphad
Home-page: https://github.com/pycalphad/pycalphad-xml
Author-email: Richard Otis <richard.otis@outlook.com>, Brandon Bocklund <brandonbocklund@gmail.com>
License: MIT License        
Project-URL: Homepage, https://github.com/pycalphad/pycalphad-xml
Platform: UNKNOWN
Classifier: Development Status :: 4 - Beta
Classifier: Intended Audience :: Science/Research
Classifier: Topic :: Scientific/Engineering :: Physics
Classifier: Topic :: Scientific/Engineering :: Chemistry
Classifier: License :: OSI Approved :: MIT License
Classifier: Programming Language :: Python :: 3
License-File: LICENSE
Requires-Dist: importlib-resources
Requires-Dist: lxml
Requires-Dist: pycalphad (>=0.10.0)
